iscp/__init__.py
iscp/_conn.py
iscp/_downstream.py
iscp/_encoding/__init__.py
iscp/_encoding/_codegen/iscp2/v1/common_pb2.py
iscp/_encoding/_codegen/iscp2/v1/connection_pb2.py
iscp/_encoding/_codegen/iscp2/v1/downstream_pb2.py
iscp/_encoding/_codegen/iscp2/v1/e2e_call_pb2.py
iscp/_encoding/_codegen/iscp2/v1/extensions/connection_pb2.py
iscp/_encoding/_codegen/iscp2/v1/extensions/downstream_pb2.py
iscp/_encoding/_codegen/iscp2/v1/extensions/e2e_call_pb2.py
iscp/_encoding/_codegen/iscp2/v1/extensions/ping_pong_pb2.py
iscp/_encoding/_codegen/iscp2/v1/extensions/upstream_pb2.py
iscp/_encoding/_codegen/iscp2/v1/message_pb2.py
iscp/_encoding/_codegen/iscp2/v1/metadata_pb2.py
iscp/_encoding/_codegen/iscp2/v1/ping_pong_pb2.py
iscp/_encoding/_codegen/iscp2/v1/result_code_pb2.py
iscp/_encoding/_codegen/iscp2/v1/upstream_pb2.py
iscp/_encoding/_encoding.py
iscp/_encoding/_protobuf/__init__.py
iscp/_encoding/_protobuf/_protobuf.py
iscp/_encoding/_protobuf/converter/__init__.py
iscp/_encoding/_protobuf/converter/_common.py
iscp/_encoding/_protobuf/converter/_connection.py
iscp/_encoding/_protobuf/converter/_converter.py
iscp/_encoding/_protobuf/converter/_downstream.py
iscp/_encoding/_protobuf/converter/_e2e_call.py
iscp/_encoding/_protobuf/converter/_metadata.py
iscp/_encoding/_protobuf/converter/_ping_pong.py
iscp/_encoding/_protobuf/converter/_result_code.py
iscp/_encoding/_protobuf/converter/_upstream.py
iscp/_exceptions/__init__.py
iscp/_exceptions/_exceptions.py
iscp/_flush_policy.py
iscp/_message/__init__.py
iscp/_message/_common.py
iscp/_message/_connection.py
iscp/_message/_downstream.py
iscp/_message/_e2e.py
iscp/_message/_message.py
iscp/_message/_metadata.py
iscp/_message/_ping_pong.py
iscp/_message/_result_code.py
iscp/_message/_upstream.py
iscp/_model.py
iscp/_sequence.py
iscp/_ticker.py
iscp/_transport/__init__.py
iscp/_transport/_negotiation_params.py
iscp/_transport/_quic.py
iscp/_transport/_transport.py
iscp/_transport/_websocket.py
iscp/_upstream.py
iscp-1.0.0.dist-info/LICENSE
iscp-1.0.0.dist-info/METADATA
iscp-1.0.0.dist-info/WHEEL
iscp-1.0.0.dist-info/RECORD
